rowifi/__init__.py
rowifi/client.py
rowifi/exceptions.py
rowifi/models.py
rowifi/utils.py
rowifi/endpoints/__init__.py
rowifi/endpoints/denylists.py
rowifi/endpoints/members.py
rowifi/endpoints/ranks.py
rowifi/endpoints/tower.py
rowifi_python-0.1.0.dist-info/licenses/LICENSE
rowifi_python-0.1.0.dist-info/METADATA
rowifi_python-0.1.0.dist-info/WHEEL
rowifi_python-0.1.0.dist-info/top_level.txt
rowifi_python-0.1.0.dist-info/RECORD
