Metadata-Version: 2.4
Name: rowifi-python
Version: 0.1.0
Summary: Async Python client for the RoWifi API
Author-email: RoWifi Team <admin@rowifi.xyz>
Project-URL: Homepage, https://github.com/peppower/rowifi-python
Project-URL: Documentation, https://rowifi.xyz/docs/api
Project-URL: Source, https://github.com/peppower/rowifi-python
Requires-Python: >=3.9
License-File: LICENSE
Requires-Dist: aiohttp>=3.9.0
Requires-Dist: pydantic>=2.0
Dynamic: license-file
